CHANGES.txt
LICENSE.txt
MANIFEST.in
README.txt
setup.py
js/__init__.py
js.angular_infinite_scroll.egg-info/PKG-INFO
js.angular_infinite_scroll.egg-info/SOURCES.txt
js.angular_infinite_scroll.egg-info/dependency_links.txt
js.angular_infinite_scroll.egg-info/entry_points.txt
js.angular_infinite_scroll.egg-info/namespace_packages.txt
js.angular_infinite_scroll.egg-info/not-zip-safe
js.angular_infinite_scroll.egg-info/requires.txt
js.angular_infinite_scroll.egg-info/top_level.txt
js/angular_infinite_scroll/__init__.py
js/angular_infinite_scroll/test_angular_infinitescroll.txt
js/angular_infinite_scroll/resources/ng-infinite-scroll.js
js/angular_infinite_scroll/resources/ng-infinite-scroll.min.js