Metadata-Version: 1.0
Name: js.angular-infinite-scroll
Version: 1.2.0
Summary: Fanstatic packaging of angular infiniteScroll
Home-page: UNKNOWN
Author: Fanstatic Developers
Author-email: fanstatic@googlegroups.com
License: BSD
Platform: UNKNOWN
